odoo/addons/website_task_state_filter/README.rst
odoo/addons/website_task_state_filter/__init__.py
odoo/addons/website_task_state_filter/__manifest__.py
odoo/addons/website_task_state_filter/controllers/__init__.py
odoo/addons/website_task_state_filter/controllers/portal_tasks.py
odoo/addons/website_task_state_filter/i18n/ca_ES.po
odoo/addons/website_task_state_filter/i18n/es.po
odoo/addons/website_task_state_filter/readme/CONTRIBUTORS.rst
odoo/addons/website_task_state_filter/readme/DESCRIPTION.rst
odoo/addons/website_task_state_filter/readme/USAGE.rst
odoo/addons/website_task_state_filter/static/description/icon.png
odoo/addons/website_task_state_filter/static/description/index.html
odoo/addons/website_task_state_filter/views/portal_search_bar.xml
odoo_addon_website_task_state_filter-16.0.1.0.0.1.dist-info/METADATA
odoo_addon_website_task_state_filter-16.0.1.0.0.1.dist-info/WHEEL
odoo_addon_website_task_state_filter-16.0.1.0.0.1.dist-info/top_level.txt
odoo_addon_website_task_state_filter-16.0.1.0.0.1.dist-info/RECORD
